MANIFEST.in
setup.cfg
setup.py
garlicsim_lib/__init__.py
garlicsim_lib/lgpl2.1_license.txt
garlicsim_lib.egg-info/PKG-INFO
garlicsim_lib.egg-info/SOURCES.txt
garlicsim_lib.egg-info/dependency_links.txt
garlicsim_lib.egg-info/not-zip-safe
garlicsim_lib.egg-info/requires.txt
garlicsim_lib.egg-info/top_level.txt
garlicsim_lib/simpacks/__init__.py
garlicsim_lib/simpacks/_endable_life_test/__init__.py
garlicsim_lib/simpacks/_endable_life_test/settings.py
garlicsim_lib/simpacks/_endable_life_test/state.py
garlicsim_lib/simpacks/_endable_life_test/wx/__init__.py
garlicsim_lib/simpacks/_endable_life_test/wx/settings.py
garlicsim_lib/simpacks/_endable_life_test/wx/widgets/__init__.py
garlicsim_lib/simpacks/_endable_life_test/wx/widgets/board_viewer.py
garlicsim_lib/simpacks/_endable_life_test/wx/widgets/state_creation_dialog.py
garlicsim_lib/simpacks/_history_test/__init__.py
garlicsim_lib/simpacks/_history_test/state.py
garlicsim_lib/simpacks/_history_test/wx/__init__.py
garlicsim_lib/simpacks/_history_test/wx/settings.py
garlicsim_lib/simpacks/_history_test/wx/widgets/__init__.py
garlicsim_lib/simpacks/_history_test/wx/widgets/state_viewer.py
garlicsim_lib/simpacks/_prisoner_persistent_test/__init__.py
garlicsim_lib/simpacks/_prisoner_persistent_test/base_player.py
garlicsim_lib/simpacks/_prisoner_persistent_test/player_type.py
garlicsim_lib/simpacks/_prisoner_persistent_test/settings.py
garlicsim_lib/simpacks/_prisoner_persistent_test/state.py
garlicsim_lib/simpacks/_prisoner_persistent_test/players/__init__.py
garlicsim_lib/simpacks/_prisoner_persistent_test/players/angel.py
garlicsim_lib/simpacks/_prisoner_persistent_test/players/devil.py
garlicsim_lib/simpacks/_prisoner_persistent_test/players/tit_for_tat.py
garlicsim_lib/simpacks/_prisoner_persistent_test/wx/__init__.py
garlicsim_lib/simpacks/_prisoner_persistent_test/wx/settings.py
garlicsim_lib/simpacks/_prisoner_persistent_test/wx/widgets/__init__.py
garlicsim_lib/simpacks/_prisoner_persistent_test/wx/widgets/state_viewer.py
garlicsim_lib/simpacks/life/__init__.py
garlicsim_lib/simpacks/life/settings.py
garlicsim_lib/simpacks/life/state.py
garlicsim_lib/simpacks/life/wx/__init__.py
garlicsim_lib/simpacks/life/wx/settings.py
