Metadata-Version: 1.1
Name: garlicsim-lib
Version: 0.6.3
Summary: Collection of GarlicSim simulation packages
Home-page: http://garlicsim.org
Author: Ram Rachum
Author-email: cool-rr@cool-rr.com
License: LGPL v2.1
Platform: UNKNOWN
Classifier: Development Status :: 3 - Alpha
Classifier: Intended Audience :: Science/Research
Classifier: License :: OSI Approved :: GNU Library or Lesser General Public License (LGPL)
Classifier: Programming Language :: Python
Classifier: Programming Language :: Python :: 2.5
Classifier: Programming Language :: Python :: 2.6
Classifier: Programming Language :: Python :: 2.7
Classifier: Topic :: Scientific/Engineering
Requires: garlicsim (== 0.6.3)
